robotframework_reportportal_updated/__init__.py
robotframework_reportportal_updated/exception.py
robotframework_reportportal_updated/listener.py
robotframework_reportportal_updated/listener.pyi
robotframework_reportportal_updated/logger.py
robotframework_reportportal_updated/model.py
robotframework_reportportal_updated/model.pyi
robotframework_reportportal_updated/post_report.py
robotframework_reportportal_updated/result_visitor.py
robotframework_reportportal_updated/result_visitor.pyi
robotframework_reportportal_updated/service.py
robotframework_reportportal_updated/service.pyi
robotframework_reportportal_updated/static.py
robotframework_reportportal_updated/static.pyi
robotframework_reportportal_updated/time_visitor.py
robotframework_reportportal_updated/variables.py
robotframework_reportportal_updated/variables.pyi
robotframework_reportportal_updated-1.1.10.dist-info/LICENSE.txt
robotframework_reportportal_updated-1.1.10.dist-info/METADATA
robotframework_reportportal_updated-1.1.10.dist-info/WHEEL
robotframework_reportportal_updated-1.1.10.dist-info/entry_points.txt
robotframework_reportportal_updated-1.1.10.dist-info/top_level.txt
robotframework_reportportal_updated-1.1.10.dist-info/RECORD
