Metadata-Version: 2.1
Name: robotframework-reportportal-updated
Version: 1.1.10
Summary: Agent for reporting RobotFramework test results to Report Portal
Home-page: https://github.com/reportportal/agent-Python-RobotFramework
Download-URL: https://github.com/reportportal/agent-Python-RobotFramework/tarball/1.1.10
Author: Report Portal Team
Author-email: support@reportportal.io
Keywords: testing,reporting,robot framework,reportportal,agent
Classifier: Framework :: Robot Framework
Classifier: Programming Language :: Python :: 3.7
Classifier: Programming Language :: Python :: 3.8
Classifier: Programming Language :: Python :: 3.9
Classifier: Programming Language :: Python :: 3.10
Classifier: Programming Language :: Python :: 3.11
License-File: LICENSE.txt
Requires-Dist: python-dateutil (>=2.8.1)
Requires-Dist: reportportal-client (==5.3.5)
Requires-Dist: robotframework
Requires-Dist: six (>=1.15.0)
